deepfense/__init__.py
deepfense/cli/__init__.py
deepfense/cli/main.py
deepfense/cli/commands/__init__.py
deepfense/cli/commands/list_components.py
deepfense/cli/commands/test.py
deepfense/cli/commands/train.py
deepfense/data/__init__.py
deepfense/data/base_dataset.py
deepfense/data/data_utils.py
deepfense/data/detection_dataset.py
deepfense/data/transforms/__init__.py
deepfense/data/transforms/audio_utils.py
deepfense/data/transforms/augmentations.py
deepfense/data/transforms/transforms.py
deepfense/data/transforms/RawBoost/RawBoost.py
deepfense/data/transforms/RawBoost/__init__.py
deepfense/data/transforms/RawBoost/data_utils_rawboost.py
deepfense/models/__init__.py
deepfense/models/base_model.py
deepfense/models/detector.py
deepfense/models/backends/__init__.py
deepfense/models/backends/aasist.py
deepfense/models/backends/ecapa_tdnn.py
deepfense/models/backends/mlp.py
deepfense/models/backends/nes2net.py
deepfense/models/backends/rawnet.py
deepfense/models/backends/tcm.py
deepfense/models/frontends/__init__.py
deepfense/models/frontends/eat.py
deepfense/models/frontends/hubert.py
deepfense/models/frontends/mert.py
deepfense/models/frontends/utils.py
deepfense/models/frontends/wav2vec2.py
deepfense/models/frontends/wavlm.py
deepfense/models/losses/__init__.py
deepfense/models/losses/a_softmax.py
deepfense/models/losses/am_softmax.py
deepfense/models/losses/cross_entropy.py
deepfense/models/losses/oc_softmax.py
deepfense/models/modules/pool.py
deepfense/models/modules/conformer/conformer.py
deepfense/models/modules/fairseq/hubconf.py
deepfense/models/modules/fairseq/release_utils.py
deepfense/models/modules/fairseq/setup.py
deepfense/models/modules/fairseq/train.py
deepfense/models/modules/fairseq/docs/conf.py
deepfense/models/modules/fairseq/examples/__init__.py
deepfense/models/modules/fairseq/examples/MMPT/locallaunch.py
deepfense/models/modules/fairseq/examples/MMPT/setup.py
deepfense/models/modules/fairseq/examples/MMPT/mmpt/__init__.py
deepfense-0.1.dist-info/METADATA
deepfense-0.1.dist-info/WHEEL
deepfense-0.1.dist-info/entry_points.txt
deepfense-0.1.dist-info/top_level.txt
deepfense-0.1.dist-info/RECORD
