Metadata-Version: 2.4
Name: deepfense
Version: 0.1
Summary: A Modular, Extensible Framework for Deepfake Audio Detection (ASV Spoofing)
Author: DeepFense Team
License: Apache-2.0
Project-URL: Homepage, https://deepfense.github.io/
Project-URL: Documentation, https://deepfense.readthedocs.io/
Project-URL: Repository, https://github.com/Yaselley/deepfense-framework
Project-URL: Issues, https://github.com/Yaselley/deepfense-framework/issues
Project-URL: Bug Tracker, https://github.com/Yaselley/deepfense-framework/issues
Project-URL: HuggingFace, https://huggingface.co/DeepFense
Keywords: deepfake,audio,spoofing,detection,asv,speech,security
Classifier: Development Status :: 3 - Alpha
Classifier: Intended Audience :: Science/Research
Classifier: License :: OSI Approved :: Apache Software License
Classifier: Programming Language :: Python :: 3
Classifier: Programming Language :: Python :: 3.10
Classifier: Programming Language :: Python :: 3.11
Classifier: Topic :: Scientific/Engineering :: Artificial Intelligence
Classifier: Topic :: Security
Requires-Python: >=3.10
Requires-Dist: torch<=2.9,>=2.1.0
Requires-Dist: torchaudio<=2.9,>=2.1.0
Requires-Dist: torchvision<=0.23,>=0.12.0
Requires-Dist: numpy<2.2,>=1.24
Requires-Dist: pandas<3.0,>=2.0
Requires-Dist: scipy<1.16,>=1.9
Requires-Dist: scikit-learn<1.8,>=1.2
Requires-Dist: pyarrow
Requires-Dist: librosa<0.12,>=0.10
Requires-Dist: pydub
Requires-Dist: soundfile
Requires-Dist: soxr
Requires-Dist: transformers<5.0,>=4.50
Requires-Dist: tokenizers
Requires-Dist: tqdm
Requires-Dist: typing-extensions
Requires-Dist: safetensors
Requires-Dist: wandb<1.0,>=0.12
Requires-Dist: einops<1.0,>=0.7
Requires-Dist: matplotlib<4.0,>=3.7
Requires-Dist: seaborn<0.14,>=0.12
Requires-Dist: timm
Requires-Dist: omegaconf==2.0.6
Requires-Dist: click>=8.0.0
Provides-Extra: dev
Requires-Dist: pytest>=7.0; extra == "dev"
Requires-Dist: black>=22.0; extra == "dev"
Requires-Dist: flake8>=4.0; extra == "dev"
